{"errors":[],"warnings":[],"namedChunkGroups":{"app":{"chunks":[7,6,3],"assets":["webpack-runtime-2c3177c1611b23f4d7ea.js","webpack-runtime-2c3177c1611b23f4d7ea.js.map","framework-81e6052b3504df28bf0b.js","framework-81e6052b3504df28bf0b.js.map","app-4bf9c18e563695ecac1b.js","app-4bf9c18e563695ecac1b.js.map"],"children":{},"childAssets":{}},"component---src-pages-about-js":{"chunks":[1,0,4],"assets":["styles.cf478406416b6145c185.css","styles-823ae8103e36ae8a7f9f.js","styles-823ae8103e36ae8a7f9f.js.map","commons-528d3d13431e63e8b71c.js","commons-528d3d13431e63e8b71c.js.map","component---src-pages-about-js-9759c0684e1282cfc4a3.js","component---src-pages-about-js-9759c0684e1282cfc4a3.js.map"],"children":{},"childAssets":{}},"component---src-pages-index-js":{"chunks":[1,2,0,5],"assets":["styles.cf478406416b6145c185.css","styles-823ae8103e36ae8a7f9f.js","styles-823ae8103e36ae8a7f9f.js.map","05d954cf-d4d46dc3334c01c9d275.js","05d954cf-d4d46dc3334c01c9d275.js.map","commons-528d3d13431e63e8b71c.js","commons-528d3d13431e63e8b71c.js.map","component---src-pages-index-js-fb99fb75aeea3a46b7c6.js","component---src-pages-index-js-fb99fb75aeea3a46b7c6.js.map"],"children":{},"childAssets":{}}},"assetsByChunkName":{"app":["webpack-runtime-2c3177c1611b23f4d7ea.js","framework-81e6052b3504df28bf0b.js","app-4bf9c18e563695ecac1b.js"],"component---src-pages-about-js":["styles.cf478406416b6145c185.css","styles-823ae8103e36ae8a7f9f.js","commons-528d3d13431e63e8b71c.js","component---src-pages-about-js-9759c0684e1282cfc4a3.js"],"component---src-pages-index-js":["styles.cf478406416b6145c185.css","styles-823ae8103e36ae8a7f9f.js","05d954cf-d4d46dc3334c01c9d275.js","commons-528d3d13431e63e8b71c.js","component---src-pages-index-js-fb99fb75aeea3a46b7c6.js"]}}