{"errors":[],"warnings":[],"namedChunkGroups":{"app":{"chunks":[7,6,3],"assets":["webpack-runtime-6dd2bac3b4381402365c.js","webpack-runtime-6dd2bac3b4381402365c.js.map","framework-81e6052b3504df28bf0b.js","framework-81e6052b3504df28bf0b.js.map","app-26ff872c2521f679e1ce.js","app-26ff872c2521f679e1ce.js.map"],"children":{},"childAssets":{}},"component---src-pages-about-js":{"chunks":[2,0,1,4],"assets":["styles.cf478406416b6145c185.css","styles-503b3015a8b38c118cb7.js","styles-503b3015a8b38c118cb7.js.map","05d954cf-ba9f5e48558e914d41ba.js","05d954cf-ba9f5e48558e914d41ba.js.map","commons-e275b02a5e8f4a2f637c.js","commons-e275b02a5e8f4a2f637c.js.map","component---src-pages-about-js-115acedc520b1b223a65.js","component---src-pages-about-js-115acedc520b1b223a65.js.map"],"children":{},"childAssets":{}},"component---src-pages-index-js":{"chunks":[2,0,1,5],"assets":["styles.cf478406416b6145c185.css","styles-503b3015a8b38c118cb7.js","styles-503b3015a8b38c118cb7.js.map","05d954cf-ba9f5e48558e914d41ba.js","05d954cf-ba9f5e48558e914d41ba.js.map","commons-e275b02a5e8f4a2f637c.js","commons-e275b02a5e8f4a2f637c.js.map","component---src-pages-index-js-ec53bb5435bd252a3bf3.js","component---src-pages-index-js-ec53bb5435bd252a3bf3.js.map"],"children":{},"childAssets":{}}},"assetsByChunkName":{"app":["webpack-runtime-6dd2bac3b4381402365c.js","framework-81e6052b3504df28bf0b.js","app-26ff872c2521f679e1ce.js"],"component---src-pages-about-js":["styles.cf478406416b6145c185.css","styles-503b3015a8b38c118cb7.js","05d954cf-ba9f5e48558e914d41ba.js","commons-e275b02a5e8f4a2f637c.js","component---src-pages-about-js-115acedc520b1b223a65.js"],"component---src-pages-index-js":["styles.cf478406416b6145c185.css","styles-503b3015a8b38c118cb7.js","05d954cf-ba9f5e48558e914d41ba.js","commons-e275b02a5e8f4a2f637c.js","component---src-pages-index-js-ec53bb5435bd252a3bf3.js"]}}